{
  "name": "kfuse-cp_group_1m_1",
  "interval": "1m",
  "rules": [
    {
      "expr": "",
      "for": "0s",
      "labels": {
        "Severity": "Warning"
      },
      "annotations": {
        "Kloudfuse Source": "{{ reReplaceAll pathPrefix \"\" externalURL }}/#/alerts/details/{{ $labels.__alert_rule_uid__ }}?folderTitle={{ reReplaceAll \" \" \"%20\"  $labels.grafana_folder }}{{ range $key, $value := $labels }}&matcher={{ $key }}%3D{{ reReplaceAll \" \" \"%20\" $value }}{{ end }}",
        "alertType": "threshold",
        "created": "2025-03-12T23:24:15.698Z",
        "extraData": "{\"queryType\":\"query\",\"queries\":[{\"isActive\":true,\"filters\":[{\"type\":\"searchTerms\",\"value\":\"Terminating due to\"},{\"type\":\"selectedFacetValue\",\"value\":{\"facet\":\"Kubernetes:!:kube_service:!:string:!:\",\"operator\":\"=~\",\"values\":{\"pinot\":1}}},{\"type\":\"selectedFacetValue\",\"value\":{\"facet\":\"Additional:!:kfuse:!:string:!:\",\"operator\":\"=\",\"values\":{\"true\":1}}}],\"limit\":{\"direction\":\"topk\",\"count\":\"10\"},\"functions\":[],\"showInput\":false,\"metric\":\"*\",\"normalizeFunction\":\"number\",\"queryKey\":\"a\",\"rangeAggregate\":\"count_over_time\",\"rangeAggregateGrouping\":[\"Additional:!:org_id:!:string\",\"Kubernetes:!:kube_cluster_name:!:string\",\"Kubernetes:!:kube_service:!:string\"],\"rangeAggregateExclude\":false,\"step\":\"15s\",\"vectorAggregate\":\"count\",\"vectorAggregateGrouping\":[],\"vectorAggregateExclude\":false,\"filtersState\":{\"state\":[{\"type\":\"searchTerms\",\"value\":\"Terminating due to\"},{\"type\":\"selectedFacetValue\",\"value\":{\"facet\":\"Kubernetes:!:kube_service:!:string:!:\",\"operator\":\"=~\",\"values\":{\"pinot\":1}}},{\"type\":\"selectedFacetValue\",\"value\":{\"facet\":\"Additional:!:kfuse:!:string:!:\",\"operator\":\"=\",\"values\":{\"true\":1}}}]},\"defaultRangeAggregateGroupingOptions\":[{\"value\":\"Additional:!:org_id:!:string\",\"label\":\"Additional:org_id\"},{\"value\":\"Kubernetes:!:kube_cluster_name:!:string\",\"label\":\"Kubernetes:kube_cluster_name\"},{\"label\":\"Kubernetes:kube_service\",\"value\":\"Kubernetes:!:kube_service:!:string\"}]}],\"formulas\":[],\"queryKey\":\"Query (a)\",\"queryLangType\":\"kfuseql\"}",
        "forWindow": "5m",
        "ruleType": "logs",
        "summary": "Pinot service out of memory"
      },
      "grafana_alert": {
        "id": 5783,
        "orgId": 1,
        "title": "Pinot service out of memory",
        "condition": "C",
        "data": [
          {
            "refId": "A",
            "queryType": "",
            "relativeTimeRange": {
              "from": 300,
              "to": 0
            },
            "datasourceUid": "P5BE00A3D5765370D",
            "model": {
              "datasource": {
                "type": "loki"
              },
              "expr": "  Terminating due to and kfuse=\"true\" and kube_service=~\"pinot\" | timeslice 15s | count by (_timeslice, org_id, kube_cluster_name, kube_service) | fields _count, _timeslice, org_id, kube_cluster_name, kube_service",
              "hide": false,
              "interval": "15s",
              "intervalMs": 15000,
              "maxDataPoints": 43200,
              "range": true,
              "refId": "A"
            }
          },
          {
            "refId": "B",
            "queryType": "",
            "relativeTimeRange": {
              "from": 0,
              "to": 0
            },
            "datasourceUid": "-100",
            "model": {
              "conditions": [
                {
                  "evaluator": {
                    "params": [
                      0
                    ],
                    "type": "gt"
                  },
                  "operator": {
                    "type": "and"
                  },
                  "query": {
                    "params": [
                      "C"
                    ]
                  },
                  "reducer": {
                    "params": [],
                    "type": "last"
                  },
                  "type": "query"
                }
              ],
              "datasource": {
                "name": "Expression",
                "type": "__expr__",
                "uid": "__expr__"
              },
              "expression": "A",
              "hide": false,
              "intervalMs": 1000,
              "maxDataPoints": 43200,
              "reducer": "last",
              "refId": "B",
              "settings": {
                "mode": "dropNN"
              },
              "type": "reduce"
            }
          },
          {
            "refId": "C",
            "queryType": "",
            "relativeTimeRange": {
              "from": 0,
              "to": 0
            },
            "datasourceUid": "-100",
            "model": {
              "conditions": [
                {
                  "evaluator": {
                    "params": [
                      0
                    ],
                    "type": "gt"
                  },
                  "operator": {
                    "type": "and"
                  },
                  "query": {
                    "params": [
                      "C"
                    ]
                  },
                  "reducer": {
                    "params": [],
                    "type": "last"
                  },
                  "type": "query"
                }
              ],
              "datasource": {
                "name": "Expression",
                "type": "__expr__",
                "uid": "__expr__"
              },
              "expression": "B",
              "hide": false,
              "intervalMs": 1000,
              "maxDataPoints": 43200,
              "refId": "C",
              "type": "threshold"
            }
          }
        ],
        "updated": "2025-04-26T22:46:06Z",
        "intervalSeconds": 60,
        "version": 25,
        "uid": "cefnt9rwt1ibke",
        "namespace_uid": "b52d4a03-cd0e-4eea-a199-546a2fc53047",
        "rule_group": "kfuse-cp_group_1m_1",
        "no_data_state": "OK",
        "exec_err_state": "KeepLast",
        "is_paused": false
      }
    }
  ]
}